PdbBBEditSupport.py
README.txt
pdbbbsupport
setup.py
PdbBBEditSupport.egg-info/PKG-INFO
PdbBBEditSupport.egg-info/SOURCES.txt
PdbBBEditSupport.egg-info/dependency_links.txt
PdbBBEditSupport.egg-info/top_level.txt