Metadata-Version: 1.0
Name: PdbBBEditSupport
Version: 1.0.1
Summary: Display source code in BBEdit while debugging in pdb
Home-page: https://bitbucket.org/schinckel/pdbbbeditsupport/
Author: Matthew Schinckel
Author-email: matt@schinckel.net
License: GPL
Keywords: bbedit pdb
Platform: Mac OS X
Classifier: Development Status :: 4 - Beta
Classifier: Environment :: Console
Classifier: Environment :: MacOS X
Classifier: Intended Audience :: Developers
Classifier: Intended Audience :: System Administrators
Classifier: License :: OSI Approved :: GNU General Public License (GPL)
Classifier: Operating System :: MacOS :: MacOS X
Classifier: Programming Language :: Python
Classifier: Topic :: Software Development :: Debuggers
Classifier: Topic :: Text Editors
